README.md
package_info.json
setup.py
th2_grpc_act_temp/__init__.py
th2_grpc_act_temp/act_template.proto
th2_grpc_act_temp/act_template_pb2.py
th2_grpc_act_temp/act_template_pb2_grpc.py
th2_grpc_act_temp/act_template_service.py
th2_grpc_act_temp.egg-info/PKG-INFO
th2_grpc_act_temp.egg-info/SOURCES.txt
th2_grpc_act_temp.egg-info/dependency_links.txt
th2_grpc_act_temp.egg-info/requires.txt
th2_grpc_act_temp.egg-info/top_level.txt