Metadata-Version: 2.1
Name: th2-grpc-act-temp
Version: 1.0.0
Summary: th2_grpc_act_temp
Home-page: https://github.com/Andrey-Zolotin/th2-grpc-act-template
Author: TH2-devs
Author-email: th2-devs@exactprosystems.com
License: Apache License 2.0
Platform: UNKNOWN
Requires-Python: >=3.7
